zonefile_parser/__init__.py
zonefile_parser/helper.py
zonefile_parser/helper_test.py
zonefile_parser/main.py
zonefile_parser/main_test.py
zonefile_parser/parser.py
zonefile_parser/record.py
zonefile_parser-0.1.18.dist-info/licenses/LICENSE.txt
zonefile_parser-0.1.18.dist-info/METADATA
zonefile_parser-0.1.18.dist-info/WHEEL
zonefile_parser-0.1.18.dist-info/top_level.txt
zonefile_parser-0.1.18.dist-info/RECORD
