Metadata-Version: 2.4
Name: zonefile_parser
Version: 0.1.18
Summary: library for parsing dns zone files
Home-page: https://github.com/aredwood/zone-file-parser
Download-URL: https://github.com/aredwood/zone-file-parser/archive/0.1.18.tar.gz
Author: Alex Redwood
Author-email: hello@alexredwood.com
Maintainer: Alex Redwood
Maintainer-email: hello@alexredwood.com
License: MIT
Keywords: parse dns zone file
Classifier: Development Status :: 3 - Alpha
Classifier: Intended Audience :: Developers
Classifier: Topic :: Software Development :: Build Tools
Classifier: License :: OSI Approved :: MIT License
Classifier: Programming Language :: Python :: 3
Classifier: Programming Language :: Python :: 3.7
Classifier: Programming Language :: Python :: 3.8
Classifier: Programming Language :: Python :: 3.9
Classifier: Programming Language :: Python :: 3.10
Classifier: Programming Language :: Python :: 3.11
License-File: LICENSE.txt
Dynamic: author
Dynamic: author-email
Dynamic: classifier
Dynamic: download-url
Dynamic: home-page
Dynamic: keywords
Dynamic: license
Dynamic: license-file
Dynamic: maintainer
Dynamic: maintainer-email
Dynamic: summary
